examples/builtin_classes/treenode_example.py
examples/custom_class/custom_class_example.py
examples/custom_class_no_serializer/point_example.py
examples/method_selection/method_selection_example.py
examples/programmatic_tree/treenode_example.py
examples/programmatic_usage/programmatic_example.py
examples/programmatic_usage/simple_example.py
examples/reverse_linklist/linked_list_solution.py
examples/solution_with_print/solution_with_prints.py
examples/testcase_retrieval/basic_usage.py
examples/valid_parentness/valid_parentness.py
pyleet/__init__.py
pyleet/__main__.py
pyleet/cli.py
pyleet/colors.py
pyleet/common.py
pyleet/datastructures.py
pyleet/programmatic.py
pyleet/runner.py
pyleet/testcase_loader.py
pyleet/testcase_retriever.py
pyleet-1.1.0.dist-info/licenses/LICENSE
pyleet-1.1.0.dist-info/METADATA
pyleet-1.1.0.dist-info/WHEEL
pyleet-1.1.0.dist-info/entry_points.txt
pyleet-1.1.0.dist-info/top_level.txt
pyleet-1.1.0.dist-info/RECORD
