Metadata-Version: 2.4
Name: pyleet
Version: 1.1.0
Summary: Run and test your LeetCode Python solutions locally
Home-page: https://github.com/ergs0204/pyleet
Author: ergs0204
Author-email: ergs0204 <ergs0204@gmail.com>
License-Expression: MIT
Project-URL: Homepage, https://github.com/ergs0204/pyleet
Project-URL: Repository, https://github.com/ergs0204/pyleet.git
Project-URL: Issues, https://github.com/ergs0204/pyleet/issues
Keywords: leetcode,pyleet
Classifier: Programming Language :: Python :: 3
Classifier: Operating System :: OS Independent
Requires-Python: >=3.7
License-File: LICENSE
Requires-Dist: requests>=2.25.0
Dynamic: author
Dynamic: home-page
Dynamic: license-file
Dynamic: requires-python
